// class version 50.0 (50)
// access flags 0x401
public abstract class TAEMultiTile$$PassThrough$class {


  // access flags 0x9
  public static $init$(LTAEMultiTile$$PassThrough;)V
    RETURN
    MAXSTACK = 1
    MAXLOCALS = 1

  // access flags 0x9
  public static bindPart(LTAEMultiTile$$PassThrough;Lcodechicken/multipart/TMultiPart;)V
    ALOAD 0
    ALOAD 1
    INVOKEINTERFACE TAEMultiTile$$PassThrough.TAEMultiTile$$PassThrough$$super$bindPart (Lcodechicken/multipart/TMultiPart;)V
    ALOAD 1
    INSTANCEOF appeng/helpers/AEMultiTile
    IFEQ L0
    ALOAD 0
    ALOAD 1
    CHECKCAST appeng/helpers/AEMultiTile
    INVOKEINTERFACE TAEMultiTile$$PassThrough.TAEMultiTile$$PassThrough$$impl_$eq (Lappeng/helpers/AEMultiTile;)V
   L0
   FRAME FULL [TAEMultiTile$$PassThrough codechicken/multipart/TMultiPart] []
    RETURN
    MAXSTACK = 2
    MAXLOCALS = 2

  // access flags 0x9
  public static partRemoved(LTAEMultiTile$$PassThrough;Lcodechicken/multipart/TMultiPart;I)V
    ALOAD 0
    ALOAD 1
    ILOAD 2
    INVOKEINTERFACE TAEMultiTile$$PassThrough.TAEMultiTile$$PassThrough$$super$partRemoved (Lcodechicken/multipart/TMultiPart;I)V
    ALOAD 1
    ALOAD 0
    INVOKEINTERFACE TAEMultiTile$$PassThrough.TAEMultiTile$$PassThrough$$impl ()Lappeng/helpers/AEMultiTile;
    IF_ACMPNE L0
    ALOAD 0
    ACONST_NULL
    INVOKEINTERFACE TAEMultiTile$$PassThrough.TAEMultiTile$$PassThrough$$impl_$eq (Lappeng/helpers/AEMultiTile;)V
   L0
   FRAME FULL [TAEMultiTile$$PassThrough codechicken/multipart/TMultiPart I] []
    RETURN
    MAXSTACK = 3
    MAXLOCALS = 3

  // access flags 0x9
  public static canAddPart(LTAEMultiTile$$PassThrough;Lcodechicken/multipart/TMultiPart;)Z
    ALOAD 0
    INVOKEINTERFACE TAEMultiTile$$PassThrough.TAEMultiTile$$PassThrough$$impl ()Lappeng/helpers/AEMultiTile;
    IFNULL L0
    ALOAD 1
    INSTANCEOF appeng/helpers/AEMultiTile
    IFEQ L0
    ICONST_0
    IRETURN
   L0
   FRAME FULL [TAEMultiTile$$PassThrough codechicken/multipart/TMultiPart] []
    ALOAD 0
    ALOAD 1
    INVOKEINTERFACE TAEMultiTile$$PassThrough.TAEMultiTile$$PassThrough$$super$canAddPart (Lcodechicken/multipart/TMultiPart;)Z
    IRETURN
    MAXSTACK = 2
    MAXLOCALS = 2

  // access flags 0x9
  public static hasRedstone(LTAEMultiTile$$PassThrough;Lnet/minecraftforge/common/util/ForgeDirection;)Z
    ALOAD 0
    INVOKEINTERFACE TAEMultiTile$$PassThrough.TAEMultiTile$$PassThrough$$impl ()Lappeng/helpers/AEMultiTile;
    ALOAD 1
    INVOKEINTERFACE appeng/helpers/AEMultiTile.hasRedstone (Lnet/minecraftforge/common/util/ForgeDirection;)Z
    IRETURN
    MAXSTACK = 2
    MAXLOCALS = 2

  // access flags 0x9
  public static removePart(LTAEMultiTile$$PassThrough;Lnet/minecraftforge/common/util/ForgeDirection;Z)V
    ALOAD 0
    INVOKEINTERFACE TAEMultiTile$$PassThrough.TAEMultiTile$$PassThrough$$impl ()Lappeng/helpers/AEMultiTile;
    ALOAD 1
    ILOAD 2
    INVOKEINTERFACE appeng/helpers/AEMultiTile.removePart (Lnet/minecraftforge/common/util/ForgeDirection;Z)V
    RETURN
    MAXSTACK = 3
    MAXLOCALS = 3

  // access flags 0x9
  public static notifyNeighbors(LTAEMultiTile$$PassThrough;)V
    ALOAD 0
    INVOKEINTERFACE TAEMultiTile$$PassThrough.TAEMultiTile$$PassThrough$$impl ()Lappeng/helpers/AEMultiTile;
    INVOKEINTERFACE appeng/helpers/AEMultiTile.notifyNeighbors ()V
    RETURN
    MAXSTACK = 1
    MAXLOCALS = 1

  // access flags 0x9
  public static partChanged(LTAEMultiTile$$PassThrough;)V
    ALOAD 0
    INVOKEINTERFACE TAEMultiTile$$PassThrough.TAEMultiTile$$PassThrough$$impl ()Lappeng/helpers/AEMultiTile;
    INVOKEINTERFACE appeng/helpers/AEMultiTile.partChanged ()V
    RETURN
    MAXSTACK = 1
    MAXLOCALS = 1

  // access flags 0x9
  public static isInWorld(LTAEMultiTile$$PassThrough;)Z
    ALOAD 0
    INVOKEINTERFACE TAEMultiTile$$PassThrough.TAEMultiTile$$PassThrough$$impl ()Lappeng/helpers/AEMultiTile;
    INVOKEINTERFACE appeng/helpers/AEMultiTile.isInWorld ()Z
    IRETURN
    MAXSTACK = 1
    MAXLOCALS = 1

  // access flags 0x9
  public static getTile(LTAEMultiTile$$PassThrough;)Lnet/minecraft/tileentity/TileEntity;
    ALOAD 0
    INVOKEINTERFACE TAEMultiTile$$PassThrough.TAEMultiTile$$PassThrough$$impl ()Lappeng/helpers/AEMultiTile;
    INVOKEINTERFACE appeng/helpers/AEMultiTile.getTile ()Lnet/minecraft/tileentity/TileEntity;
    ARETURN
    MAXSTACK = 1
    MAXLOCALS = 1

  // access flags 0x9
  public static getPart(LTAEMultiTile$$PassThrough;Lnet/minecraftforge/common/util/ForgeDirection;)Lappeng/api/parts/IPart;
    ALOAD 0
    INVOKEINTERFACE TAEMultiTile$$PassThrough.TAEMultiTile$$PassThrough$$impl ()Lappeng/helpers/AEMultiTile;
    ALOAD 1
    INVOKEINTERFACE appeng/helpers/AEMultiTile.getPart (Lnet/minecraftforge/common/util/ForgeDirection;)Lappeng/api/parts/IPart;
    ARETURN
    MAXSTACK = 2
    MAXLOCALS = 2

  // access flags 0x9
  public static selectPart(LTAEMultiTile$$PassThrough;Lnet/minecraft/util/Vec3;)Lappeng/api/parts/SelectedPart;
    ALOAD 0
    INVOKEINTERFACE TAEMultiTile$$PassThrough.TAEMultiTile$$PassThrough$$impl ()Lappeng/helpers/AEMultiTile;
    ALOAD 1
    INVOKEINTERFACE appeng/helpers/AEMultiTile.selectPart (Lnet/minecraft/util/Vec3;)Lappeng/api/parts/SelectedPart;
    ARETURN
    MAXSTACK = 2
    MAXLOCALS = 2

  // access flags 0x9
  public static securityBreak(LTAEMultiTile$$PassThrough;)V
    ALOAD 0
    INVOKEINTERFACE TAEMultiTile$$PassThrough.TAEMultiTile$$PassThrough$$impl ()Lappeng/helpers/AEMultiTile;
    INVOKEINTERFACE appeng/helpers/AEMultiTile.securityBreak ()V
    RETURN
    MAXSTACK = 1
    MAXLOCALS = 1

  // access flags 0x9
  public static getGridNode(LTAEMultiTile$$PassThrough;Lnet/minecraftforge/common/util/ForgeDirection;)Lappeng/api/networking/IGridNode;
    ALOAD 0
    INVOKEINTERFACE TAEMultiTile$$PassThrough.TAEMultiTile$$PassThrough$$impl ()Lappeng/helpers/AEMultiTile;
    ALOAD 1
    INVOKEINTERFACE appeng/helpers/AEMultiTile.getGridNode (Lnet/minecraftforge/common/util/ForgeDirection;)Lappeng/api/networking/IGridNode;
    ARETURN
    MAXSTACK = 2
    MAXLOCALS = 2

  // access flags 0x9
  public static getLayerFlags(LTAEMultiTile$$PassThrough;)Ljava/util/Set;
    ALOAD 0
    INVOKEINTERFACE TAEMultiTile$$PassThrough.TAEMultiTile$$PassThrough$$impl ()Lappeng/helpers/AEMultiTile;
    INVOKEINTERFACE appeng/helpers/AEMultiTile.getLayerFlags ()Ljava/util/Set;
    ARETURN
    MAXSTACK = 1
    MAXLOCALS = 1

  // access flags 0x9
  public static addPart(LTAEMultiTile$$PassThrough;Lnet/minecraft/item/ItemStack;Lnet/minecraftforge/common/util/ForgeDirection;Lnet/minecraft/entity/player/EntityPlayer;)Lnet/minecraftforge/common/util/ForgeDirection;
    ALOAD 0
    INVOKEINTERFACE TAEMultiTile$$PassThrough.TAEMultiTile$$PassThrough$$impl ()Lappeng/helpers/AEMultiTile;
    ALOAD 1
    ALOAD 2
    ALOAD 3
    INVOKEINTERFACE appeng/helpers/AEMultiTile.addPart (Lnet/minecraft/item/ItemStack;Lnet/minecraftforge/common/util/ForgeDirection;Lnet/minecraft/entity/player/EntityPlayer;)Lnet/minecraftforge/common/util/ForgeDirection;
    ARETURN
    MAXSTACK = 4
    MAXLOCALS = 4

  // access flags 0x9
  public static isEmpty(LTAEMultiTile$$PassThrough;)Z
    ALOAD 0
    INVOKEINTERFACE TAEMultiTile$$PassThrough.TAEMultiTile$$PassThrough$$impl ()Lappeng/helpers/AEMultiTile;
    INVOKEINTERFACE appeng/helpers/AEMultiTile.isEmpty ()Z
    IRETURN
    MAXSTACK = 1
    MAXLOCALS = 1

  // access flags 0x9
  public static getFacadeContainer(LTAEMultiTile$$PassThrough;)Lappeng/api/parts/IFacadeContainer;
    ALOAD 0
    INVOKEINTERFACE TAEMultiTile$$PassThrough.TAEMultiTile$$PassThrough$$impl ()Lappeng/helpers/AEMultiTile;
    INVOKEINTERFACE appeng/helpers/AEMultiTile.getFacadeContainer ()Lappeng/api/parts/IFacadeContainer;
    ARETURN
    MAXSTACK = 1
    MAXLOCALS = 1

  // access flags 0x9
  public static isBlocked(LTAEMultiTile$$PassThrough;Lnet/minecraftforge/common/util/ForgeDirection;)Z
    ALOAD 0
    INVOKEINTERFACE TAEMultiTile$$PassThrough.TAEMultiTile$$PassThrough$$impl ()Lappeng/helpers/AEMultiTile;
    ALOAD 1
    INVOKEINTERFACE appeng/helpers/AEMultiTile.isBlocked (Lnet/minecraftforge/common/util/ForgeDirection;)Z
    IRETURN
    MAXSTACK = 2
    MAXLOCALS = 2

  // access flags 0x9
  public static getColor(LTAEMultiTile$$PassThrough;)Lappeng/api/util/AEColor;
    ALOAD 0
    INVOKEINTERFACE TAEMultiTile$$PassThrough.TAEMultiTile$$PassThrough$$impl ()Lappeng/helpers/AEMultiTile;
    INVOKEINTERFACE appeng/helpers/AEMultiTile.getColor ()Lappeng/api/util/AEColor;
    ARETURN
    MAXSTACK = 1
    MAXLOCALS = 1

  // access flags 0x9
  public static cleanup(LTAEMultiTile$$PassThrough;)V
    ALOAD 0
    INVOKEINTERFACE TAEMultiTile$$PassThrough.TAEMultiTile$$PassThrough$$impl ()Lappeng/helpers/AEMultiTile;
    INVOKEINTERFACE appeng/helpers/AEMultiTile.cleanup ()V
    RETURN
    MAXSTACK = 1
    MAXLOCALS = 1

  // access flags 0x9
  public static clearContainer(LTAEMultiTile$$PassThrough;)V
    ALOAD 0
    INVOKEINTERFACE TAEMultiTile$$PassThrough.TAEMultiTile$$PassThrough$$impl ()Lappeng/helpers/AEMultiTile;
    INVOKEINTERFACE appeng/helpers/AEMultiTile.clearContainer ()V
    RETURN
    MAXSTACK = 1
    MAXLOCALS = 1

  // access flags 0x9
  public static canAddPart(LTAEMultiTile$$PassThrough;Lnet/minecraft/item/ItemStack;Lnet/minecraftforge/common/util/ForgeDirection;)Z
    ALOAD 0
    INVOKEINTERFACE TAEMultiTile$$PassThrough.TAEMultiTile$$PassThrough$$impl ()Lappeng/helpers/AEMultiTile;
    ALOAD 1
    ALOAD 2
    INVOKEINTERFACE appeng/helpers/AEMultiTile.canAddPart (Lnet/minecraft/item/ItemStack;Lnet/minecraftforge/common/util/ForgeDirection;)Z
    IRETURN
    MAXSTACK = 3
    MAXLOCALS = 3

  // access flags 0x9
  public static getLocation(LTAEMultiTile$$PassThrough;)Lappeng/api/util/DimensionalCoord;
    ALOAD 0
    INVOKEINTERFACE TAEMultiTile$$PassThrough.TAEMultiTile$$PassThrough$$impl ()Lappeng/helpers/AEMultiTile;
    INVOKEINTERFACE appeng/helpers/AEMultiTile.getLocation ()Lappeng/api/util/DimensionalCoord;
    ARETURN
    MAXSTACK = 1
    MAXLOCALS = 1

  // access flags 0x9
  public static markForUpdate(LTAEMultiTile$$PassThrough;)V
    ALOAD 0
    INVOKEINTERFACE TAEMultiTile$$PassThrough.TAEMultiTile$$PassThrough$$impl ()Lappeng/helpers/AEMultiTile;
    INVOKEINTERFACE appeng/helpers/AEMultiTile.markForUpdate ()V
    RETURN
    MAXSTACK = 1
    MAXLOCALS = 1

  // access flags 0x9
  public static recolourBlock(LTAEMultiTile$$PassThrough;Lnet/minecraftforge/common/util/ForgeDirection;Lappeng/api/util/AEColor;Lnet/minecraft/entity/player/EntityPlayer;)Z
    ALOAD 0
    INVOKEINTERFACE TAEMultiTile$$PassThrough.TAEMultiTile$$PassThrough$$impl ()Lappeng/helpers/AEMultiTile;
    ALOAD 1
    ALOAD 2
    ALOAD 3
    INVOKEINTERFACE appeng/helpers/AEMultiTile.recolourBlock (Lnet/minecraftforge/common/util/ForgeDirection;Lappeng/api/util/AEColor;Lnet/minecraft/entity/player/EntityPlayer;)Z
    IRETURN
    MAXSTACK = 4
    MAXLOCALS = 4

  // access flags 0x9
  public static markForSave(LTAEMultiTile$$PassThrough;)V
    ALOAD 0
    INVOKEINTERFACE TAEMultiTile$$PassThrough.TAEMultiTile$$PassThrough$$impl ()Lappeng/helpers/AEMultiTile;
    INVOKEINTERFACE appeng/helpers/AEMultiTile.markForSave ()V
    RETURN
    MAXSTACK = 1
    MAXLOCALS = 1

  // access flags 0x9
  public static getCableConnectionType(LTAEMultiTile$$PassThrough;Lnet/minecraftforge/common/util/ForgeDirection;)Lappeng/api/util/AECableType;
    ALOAD 0
    INVOKEINTERFACE TAEMultiTile$$PassThrough.TAEMultiTile$$PassThrough$$impl ()Lappeng/helpers/AEMultiTile;
    ALOAD 1
    INVOKEINTERFACE appeng/helpers/AEMultiTile.getCableConnectionType (Lnet/minecraftforge/common/util/ForgeDirection;)Lappeng/api/util/AECableType;
    ARETURN
    MAXSTACK = 2
    MAXLOCALS = 2

  // access flags 0x9
  public static copyFrom(LTAEMultiTile$$PassThrough;Lcodechicken/multipart/TileMultipart;)V
    ALOAD 0
    ALOAD 1
    INVOKEINTERFACE TAEMultiTile$$PassThrough.TAEMultiTile$$PassThrough$$super$copyFrom (Lcodechicken/multipart/TileMultipart;)V
    ALOAD 1
    INSTANCEOF TAEMultiTile$$PassThrough
    IFEQ L0
    ALOAD 0
    ALOAD 1
    INVOKEINTERFACE TAEMultiTile$$PassThrough.TAEMultiTile$$PassThrough$$impl ()Lappeng/helpers/AEMultiTile;
    INVOKEINTERFACE TAEMultiTile$$PassThrough.TAEMultiTile$$PassThrough$$impl_$eq (Lappeng/helpers/AEMultiTile;)V
   L0
    RETURN
    MAXSTACK = 2
    MAXLOCALS = 2
}
