// class version 50.0 (50)
// access flags 0x401
public abstract class TAntiMobTorch$$PassThrough$class {


  // access flags 0x9
  public static $init$(LTAntiMobTorch$$PassThrough;)V
    RETURN
    MAXSTACK = 1
    MAXLOCALS = 1

  // access flags 0x9
  public static bindPart(LTAntiMobTorch$$PassThrough;Lcodechicken/multipart/TMultiPart;)V
    ALOAD 0
    ALOAD 1
    INVOKEINTERFACE TAntiMobTorch$$PassThrough.TAntiMobTorch$$PassThrough$$super$bindPart (Lcodechicken/multipart/TMultiPart;)V
    ALOAD 1
    INSTANCEOF com/rwtema/extrautils/tileentity/IAntiMobTorch
    IFEQ L0
    ALOAD 0
    ALOAD 1
    CHECKCAST com/rwtema/extrautils/tileentity/IAntiMobTorch
    INVOKEINTERFACE TAntiMobTorch$$PassThrough.TAntiMobTorch$$PassThrough$$impl_$eq (Lcom/rwtema/extrautils/tileentity/IAntiMobTorch;)V
   L0
   FRAME FULL [TAntiMobTorch$$PassThrough codechicken/multipart/TMultiPart] []
    RETURN
    MAXSTACK = 2
    MAXLOCALS = 2

  // access flags 0x9
  public static partRemoved(LTAntiMobTorch$$PassThrough;Lcodechicken/multipart/TMultiPart;I)V
    ALOAD 0
    ALOAD 1
    ILOAD 2
    INVOKEINTERFACE TAntiMobTorch$$PassThrough.TAntiMobTorch$$PassThrough$$super$partRemoved (Lcodechicken/multipart/TMultiPart;I)V
    ALOAD 1
    ALOAD 0
    INVOKEINTERFACE TAntiMobTorch$$PassThrough.TAntiMobTorch$$PassThrough$$impl ()Lcom/rwtema/extrautils/tileentity/IAntiMobTorch;
    IF_ACMPNE L0
    ALOAD 0
    ACONST_NULL
    INVOKEINTERFACE TAntiMobTorch$$PassThrough.TAntiMobTorch$$PassThrough$$impl_$eq (Lcom/rwtema/extrautils/tileentity/IAntiMobTorch;)V
   L0
   FRAME FULL [TAntiMobTorch$$PassThrough codechicken/multipart/TMultiPart I] []
    RETURN
    MAXSTACK = 3
    MAXLOCALS = 3

  // access flags 0x9
  public static canAddPart(LTAntiMobTorch$$PassThrough;Lcodechicken/multipart/TMultiPart;)Z
    ALOAD 0
    INVOKEINTERFACE TAntiMobTorch$$PassThrough.TAntiMobTorch$$PassThrough$$impl ()Lcom/rwtema/extrautils/tileentity/IAntiMobTorch;
    IFNULL L0
    ALOAD 1
    INSTANCEOF com/rwtema/extrautils/tileentity/IAntiMobTorch
    IFEQ L0
    ICONST_0
    IRETURN
   L0
   FRAME FULL [TAntiMobTorch$$PassThrough codechicken/multipart/TMultiPart] []
    ALOAD 0
    ALOAD 1
    INVOKEINTERFACE TAntiMobTorch$$PassThrough.TAntiMobTorch$$PassThrough$$super$canAddPart (Lcodechicken/multipart/TMultiPart;)Z
    IRETURN
    MAXSTACK = 2
    MAXLOCALS = 2

  // access flags 0x9
  public static getHorizontalTorchRangeSquared(LTAntiMobTorch$$PassThrough;)F
    ALOAD 0
    INVOKEINTERFACE TAntiMobTorch$$PassThrough.TAntiMobTorch$$PassThrough$$impl ()Lcom/rwtema/extrautils/tileentity/IAntiMobTorch;
    INVOKEINTERFACE com/rwtema/extrautils/tileentity/IAntiMobTorch.getHorizontalTorchRangeSquared ()F
    FRETURN
    MAXSTACK = 1
    MAXLOCALS = 1

  // access flags 0x9
  public static getVerticalTorchRangeSquared(LTAntiMobTorch$$PassThrough;)F
    ALOAD 0
    INVOKEINTERFACE TAntiMobTorch$$PassThrough.TAntiMobTorch$$PassThrough$$impl ()Lcom/rwtema/extrautils/tileentity/IAntiMobTorch;
    INVOKEINTERFACE com/rwtema/extrautils/tileentity/IAntiMobTorch.getVerticalTorchRangeSquared ()F
    FRETURN
    MAXSTACK = 1
    MAXLOCALS = 1

  // access flags 0x9
  public static copyFrom(LTAntiMobTorch$$PassThrough;Lcodechicken/multipart/TileMultipart;)V
    ALOAD 0
    ALOAD 1
    INVOKEINTERFACE TAntiMobTorch$$PassThrough.TAntiMobTorch$$PassThrough$$super$copyFrom (Lcodechicken/multipart/TileMultipart;)V
    ALOAD 1
    INSTANCEOF TAntiMobTorch$$PassThrough
    IFEQ L0
    ALOAD 0
    ALOAD 1
    INVOKEINTERFACE TAntiMobTorch$$PassThrough.TAntiMobTorch$$PassThrough$$impl ()Lcom/rwtema/extrautils/tileentity/IAntiMobTorch;
    INVOKEINTERFACE TAntiMobTorch$$PassThrough.TAntiMobTorch$$PassThrough$$impl_$eq (Lcom/rwtema/extrautils/tileentity/IAntiMobTorch;)V
   L0
    RETURN
    MAXSTACK = 2
    MAXLOCALS = 2
}
