// class version 50.0 (50)
// access flags 0x401
public abstract class TEnergyConnected$$PassThrough$class {


  // access flags 0x9
  public static $init$(LTEnergyConnected$$PassThrough;)V
    RETURN
    MAXSTACK = 1
    MAXLOCALS = 1

  // access flags 0x9
  public static bindPart(LTEnergyConnected$$PassThrough;Lcodechicken/multipart/TMultiPart;)V
    ALOAD 0
    ALOAD 1
    INVOKEINTERFACE TEnergyConnected$$PassThrough.TEnergyConnected$$PassThrough$$super$bindPart (Lcodechicken/multipart/TMultiPart;)V
    ALOAD 1
    INSTANCEOF gregtech/api/interfaces/tileentity/IEnergyConnected
    IFEQ L0
    ALOAD 0
    ALOAD 1
    CHECKCAST gregtech/api/interfaces/tileentity/IEnergyConnected
    INVOKEINTERFACE TEnergyConnected$$PassThrough.TEnergyConnected$$PassThrough$$impl_$eq (Lgregtech/api/interfaces/tileentity/IEnergyConnected;)V
   L0
   FRAME FULL [TEnergyConnected$$PassThrough codechicken/multipart/TMultiPart] []
    RETURN
    MAXSTACK = 2
    MAXLOCALS = 2

  // access flags 0x9
  public static partRemoved(LTEnergyConnected$$PassThrough;Lcodechicken/multipart/TMultiPart;I)V
    ALOAD 0
    ALOAD 1
    ILOAD 2
    INVOKEINTERFACE TEnergyConnected$$PassThrough.TEnergyConnected$$PassThrough$$super$partRemoved (Lcodechicken/multipart/TMultiPart;I)V
    ALOAD 1
    ALOAD 0
    INVOKEINTERFACE TEnergyConnected$$PassThrough.TEnergyConnected$$PassThrough$$impl ()Lgregtech/api/interfaces/tileentity/IEnergyConnected;
    IF_ACMPNE L0
    ALOAD 0
    ACONST_NULL
    INVOKEINTERFACE TEnergyConnected$$PassThrough.TEnergyConnected$$PassThrough$$impl_$eq (Lgregtech/api/interfaces/tileentity/IEnergyConnected;)V
   L0
   FRAME FULL [TEnergyConnected$$PassThrough codechicken/multipart/TMultiPart I] []
    RETURN
    MAXSTACK = 3
    MAXLOCALS = 3

  // access flags 0x9
  public static canAddPart(LTEnergyConnected$$PassThrough;Lcodechicken/multipart/TMultiPart;)Z
    ALOAD 0
    INVOKEINTERFACE TEnergyConnected$$PassThrough.TEnergyConnected$$PassThrough$$impl ()Lgregtech/api/interfaces/tileentity/IEnergyConnected;
    IFNULL L0
    ALOAD 1
    INSTANCEOF gregtech/api/interfaces/tileentity/IEnergyConnected
    IFEQ L0
    ICONST_0
    IRETURN
   L0
   FRAME FULL [TEnergyConnected$$PassThrough codechicken/multipart/TMultiPart] []
    ALOAD 0
    ALOAD 1
    INVOKEINTERFACE TEnergyConnected$$PassThrough.TEnergyConnected$$PassThrough$$super$canAddPart (Lcodechicken/multipart/TMultiPart;)Z
    IRETURN
    MAXSTACK = 2
    MAXLOCALS = 2

  // access flags 0x9
  public static inputEnergyFrom(LTEnergyConnected$$PassThrough;Lnet/minecraftforge/common/util/ForgeDirection;Z)Z
    ALOAD 0
    INVOKEINTERFACE TEnergyConnected$$PassThrough.TEnergyConnected$$PassThrough$$impl ()Lgregtech/api/interfaces/tileentity/IEnergyConnected;
    ALOAD 1
    ILOAD 2
    INVOKEINTERFACE gregtech/api/interfaces/tileentity/IEnergyConnected.inputEnergyFrom (Lnet/minecraftforge/common/util/ForgeDirection;Z)Z
    IRETURN
    MAXSTACK = 3
    MAXLOCALS = 3

  // access flags 0x9
  public static getColorization(LTEnergyConnected$$PassThrough;)B
    ALOAD 0
    INVOKEINTERFACE TEnergyConnected$$PassThrough.TEnergyConnected$$PassThrough$$impl ()Lgregtech/api/interfaces/tileentity/IEnergyConnected;
    INVOKEINTERFACE gregtech/api/interfaces/tileentity/IEnergyConnected.getColorization ()B
    IRETURN
    MAXSTACK = 1
    MAXLOCALS = 1

  // access flags 0x9
  public static injectEnergyUnits(LTEnergyConnected$$PassThrough;Lnet/minecraftforge/common/util/ForgeDirection;JJ)J
    ALOAD 0
    INVOKEINTERFACE TEnergyConnected$$PassThrough.TEnergyConnected$$PassThrough$$impl ()Lgregtech/api/interfaces/tileentity/IEnergyConnected;
    ALOAD 1
    LLOAD 2
    LLOAD 4
    INVOKEINTERFACE gregtech/api/interfaces/tileentity/IEnergyConnected.injectEnergyUnits (Lnet/minecraftforge/common/util/ForgeDirection;JJ)J
    LRETURN
    MAXSTACK = 6
    MAXLOCALS = 6

  // access flags 0x9
  public static inputEnergyFrom(LTEnergyConnected$$PassThrough;Lnet/minecraftforge/common/util/ForgeDirection;)Z
    ALOAD 0
    INVOKEINTERFACE TEnergyConnected$$PassThrough.TEnergyConnected$$PassThrough$$impl ()Lgregtech/api/interfaces/tileentity/IEnergyConnected;
    ALOAD 1
    INVOKEINTERFACE gregtech/api/interfaces/tileentity/IEnergyConnected.inputEnergyFrom (Lnet/minecraftforge/common/util/ForgeDirection;)Z
    IRETURN
    MAXSTACK = 2
    MAXLOCALS = 2

  // access flags 0x9
  public static outputsEnergyTo(LTEnergyConnected$$PassThrough;Lnet/minecraftforge/common/util/ForgeDirection;Z)Z
    ALOAD 0
    INVOKEINTERFACE TEnergyConnected$$PassThrough.TEnergyConnected$$PassThrough$$impl ()Lgregtech/api/interfaces/tileentity/IEnergyConnected;
    ALOAD 1
    ILOAD 2
    INVOKEINTERFACE gregtech/api/interfaces/tileentity/IEnergyConnected.outputsEnergyTo (Lnet/minecraftforge/common/util/ForgeDirection;Z)Z
    IRETURN
    MAXSTACK = 3
    MAXLOCALS = 3

  // access flags 0x9
  public static outputsEnergyTo(LTEnergyConnected$$PassThrough;Lnet/minecraftforge/common/util/ForgeDirection;)Z
    ALOAD 0
    INVOKEINTERFACE TEnergyConnected$$PassThrough.TEnergyConnected$$PassThrough$$impl ()Lgregtech/api/interfaces/tileentity/IEnergyConnected;
    ALOAD 1
    INVOKEINTERFACE gregtech/api/interfaces/tileentity/IEnergyConnected.outputsEnergyTo (Lnet/minecraftforge/common/util/ForgeDirection;)Z
    IRETURN
    MAXSTACK = 2
    MAXLOCALS = 2

  // access flags 0x9
  public static getGUIColorization(LTEnergyConnected$$PassThrough;)I
    ALOAD 0
    INVOKEINTERFACE TEnergyConnected$$PassThrough.TEnergyConnected$$PassThrough$$impl ()Lgregtech/api/interfaces/tileentity/IEnergyConnected;
    INVOKEINTERFACE gregtech/api/interfaces/tileentity/IEnergyConnected.getGUIColorization ()I
    IRETURN
    MAXSTACK = 1
    MAXLOCALS = 1

  // access flags 0x9
  public static setColorization(LTEnergyConnected$$PassThrough;B)B
    ALOAD 0
    INVOKEINTERFACE TEnergyConnected$$PassThrough.TEnergyConnected$$PassThrough$$impl ()Lgregtech/api/interfaces/tileentity/IEnergyConnected;
    ILOAD 1
    INVOKEINTERFACE gregtech/api/interfaces/tileentity/IEnergyConnected.setColorization (B)B
    IRETURN
    MAXSTACK = 2
    MAXLOCALS = 2

  // access flags 0x9
  public static copyFrom(LTEnergyConnected$$PassThrough;Lcodechicken/multipart/TileMultipart;)V
    ALOAD 0
    ALOAD 1
    INVOKEINTERFACE TEnergyConnected$$PassThrough.TEnergyConnected$$PassThrough$$super$copyFrom (Lcodechicken/multipart/TileMultipart;)V
    ALOAD 1
    INSTANCEOF TEnergyConnected$$PassThrough
    IFEQ L0
    ALOAD 0
    ALOAD 1
    INVOKEINTERFACE TEnergyConnected$$PassThrough.TEnergyConnected$$PassThrough$$impl ()Lgregtech/api/interfaces/tileentity/IEnergyConnected;
    INVOKEINTERFACE TEnergyConnected$$PassThrough.TEnergyConnected$$PassThrough$$impl_$eq (Lgregtech/api/interfaces/tileentity/IEnergyConnected;)V
   L0
    RETURN
    MAXSTACK = 2
    MAXLOCALS = 2
}
