// class version 50.0 (50)
// access flags 0x401
public abstract class TEnergyHandler$$PassThrough$class {


  // access flags 0x9
  public static $init$(LTEnergyHandler$$PassThrough;)V
    RETURN
    MAXSTACK = 1
    MAXLOCALS = 1

  // access flags 0x9
  public static bindPart(LTEnergyHandler$$PassThrough;Lcodechicken/multipart/TMultiPart;)V
    ALOAD 0
    ALOAD 1
    INVOKEINTERFACE TEnergyHandler$$PassThrough.TEnergyHandler$$PassThrough$$super$bindPart (Lcodechicken/multipart/TMultiPart;)V
    ALOAD 1
    INSTANCEOF cofh/api/energy/IEnergyHandler
    IFEQ L0
    ALOAD 0
    ALOAD 1
    CHECKCAST cofh/api/energy/IEnergyHandler
    INVOKEINTERFACE TEnergyHandler$$PassThrough.TEnergyHandler$$PassThrough$$impl_$eq (Lcofh/api/energy/IEnergyHandler;)V
   L0
   FRAME FULL [TEnergyHandler$$PassThrough codechicken/multipart/TMultiPart] []
    RETURN
    MAXSTACK = 2
    MAXLOCALS = 2

  // access flags 0x9
  public static partRemoved(LTEnergyHandler$$PassThrough;Lcodechicken/multipart/TMultiPart;I)V
    ALOAD 0
    ALOAD 1
    ILOAD 2
    INVOKEINTERFACE TEnergyHandler$$PassThrough.TEnergyHandler$$PassThrough$$super$partRemoved (Lcodechicken/multipart/TMultiPart;I)V
    ALOAD 1
    ALOAD 0
    INVOKEINTERFACE TEnergyHandler$$PassThrough.TEnergyHandler$$PassThrough$$impl ()Lcofh/api/energy/IEnergyHandler;
    IF_ACMPNE L0
    ALOAD 0
    ACONST_NULL
    INVOKEINTERFACE TEnergyHandler$$PassThrough.TEnergyHandler$$PassThrough$$impl_$eq (Lcofh/api/energy/IEnergyHandler;)V
   L0
   FRAME FULL [TEnergyHandler$$PassThrough codechicken/multipart/TMultiPart I] []
    RETURN
    MAXSTACK = 3
    MAXLOCALS = 3

  // access flags 0x9
  public static canAddPart(LTEnergyHandler$$PassThrough;Lcodechicken/multipart/TMultiPart;)Z
    ALOAD 0
    INVOKEINTERFACE TEnergyHandler$$PassThrough.TEnergyHandler$$PassThrough$$impl ()Lcofh/api/energy/IEnergyHandler;
    IFNULL L0
    ALOAD 1
    INSTANCEOF cofh/api/energy/IEnergyHandler
    IFEQ L0
    ICONST_0
    IRETURN
   L0
   FRAME FULL [TEnergyHandler$$PassThrough codechicken/multipart/TMultiPart] []
    ALOAD 0
    ALOAD 1
    INVOKEINTERFACE TEnergyHandler$$PassThrough.TEnergyHandler$$PassThrough$$super$canAddPart (Lcodechicken/multipart/TMultiPart;)Z
    IRETURN
    MAXSTACK = 2
    MAXLOCALS = 2

  // access flags 0x9
  public static getEnergyStored(LTEnergyHandler$$PassThrough;Lnet/minecraftforge/common/util/ForgeDirection;)I
    ALOAD 0
    INVOKEINTERFACE TEnergyHandler$$PassThrough.TEnergyHandler$$PassThrough$$impl ()Lcofh/api/energy/IEnergyHandler;
    ALOAD 1
    INVOKEINTERFACE cofh/api/energy/IEnergyHandler.getEnergyStored (Lnet/minecraftforge/common/util/ForgeDirection;)I
    IRETURN
    MAXSTACK = 2
    MAXLOCALS = 2

  // access flags 0x9
  public static extractEnergy(LTEnergyHandler$$PassThrough;Lnet/minecraftforge/common/util/ForgeDirection;IZ)I
    ALOAD 0
    INVOKEINTERFACE TEnergyHandler$$PassThrough.TEnergyHandler$$PassThrough$$impl ()Lcofh/api/energy/IEnergyHandler;
    ALOAD 1
    ILOAD 2
    ILOAD 3
    INVOKEINTERFACE cofh/api/energy/IEnergyHandler.extractEnergy (Lnet/minecraftforge/common/util/ForgeDirection;IZ)I
    IRETURN
    MAXSTACK = 4
    MAXLOCALS = 4

  // access flags 0x9
  public static canConnectEnergy(LTEnergyHandler$$PassThrough;Lnet/minecraftforge/common/util/ForgeDirection;)Z
    ALOAD 0
    INVOKEINTERFACE TEnergyHandler$$PassThrough.TEnergyHandler$$PassThrough$$impl ()Lcofh/api/energy/IEnergyHandler;
    ALOAD 1
    INVOKEINTERFACE cofh/api/energy/IEnergyHandler.canConnectEnergy (Lnet/minecraftforge/common/util/ForgeDirection;)Z
    IRETURN
    MAXSTACK = 2
    MAXLOCALS = 2

  // access flags 0x9
  public static receiveEnergy(LTEnergyHandler$$PassThrough;Lnet/minecraftforge/common/util/ForgeDirection;IZ)I
    ALOAD 0
    INVOKEINTERFACE TEnergyHandler$$PassThrough.TEnergyHandler$$PassThrough$$impl ()Lcofh/api/energy/IEnergyHandler;
    ALOAD 1
    ILOAD 2
    ILOAD 3
    INVOKEINTERFACE cofh/api/energy/IEnergyHandler.receiveEnergy (Lnet/minecraftforge/common/util/ForgeDirection;IZ)I
    IRETURN
    MAXSTACK = 4
    MAXLOCALS = 4

  // access flags 0x9
  public static getMaxEnergyStored(LTEnergyHandler$$PassThrough;Lnet/minecraftforge/common/util/ForgeDirection;)I
    ALOAD 0
    INVOKEINTERFACE TEnergyHandler$$PassThrough.TEnergyHandler$$PassThrough$$impl ()Lcofh/api/energy/IEnergyHandler;
    ALOAD 1
    INVOKEINTERFACE cofh/api/energy/IEnergyHandler.getMaxEnergyStored (Lnet/minecraftforge/common/util/ForgeDirection;)I
    IRETURN
    MAXSTACK = 2
    MAXLOCALS = 2

  // access flags 0x9
  public static copyFrom(LTEnergyHandler$$PassThrough;Lcodechicken/multipart/TileMultipart;)V
    ALOAD 0
    ALOAD 1
    INVOKEINTERFACE TEnergyHandler$$PassThrough.TEnergyHandler$$PassThrough$$super$copyFrom (Lcodechicken/multipart/TileMultipart;)V
    ALOAD 1
    INSTANCEOF TEnergyHandler$$PassThrough
    IFEQ L0
    ALOAD 0
    ALOAD 1
    INVOKEINTERFACE TEnergyHandler$$PassThrough.TEnergyHandler$$PassThrough$$impl ()Lcofh/api/energy/IEnergyHandler;
    INVOKEINTERFACE TEnergyHandler$$PassThrough.TEnergyHandler$$PassThrough$$impl_$eq (Lcofh/api/energy/IEnergyHandler;)V
   L0
    RETURN
    MAXSTACK = 2
    MAXLOCALS = 2
}
