// class version 50.0 (50)
// access flags 0x401
public abstract class TFence$$PassThrough$class {


  // access flags 0x9
  public static $init$(LTFence$$PassThrough;)V
    RETURN
    MAXSTACK = 1
    MAXLOCALS = 1

  // access flags 0x9
  public static bindPart(LTFence$$PassThrough;Lcodechicken/multipart/TMultiPart;)V
    ALOAD 0
    ALOAD 1
    INVOKEINTERFACE TFence$$PassThrough.TFence$$PassThrough$$super$bindPart (Lcodechicken/multipart/TMultiPart;)V
    ALOAD 1
    INSTANCEOF com/rwtema/extrautils/multipart/microblock/IFence
    IFEQ L0
    ALOAD 0
    ALOAD 1
    CHECKCAST com/rwtema/extrautils/multipart/microblock/IFence
    INVOKEINTERFACE TFence$$PassThrough.TFence$$PassThrough$$impl_$eq (Lcom/rwtema/extrautils/multipart/microblock/IFence;)V
   L0
   FRAME FULL [TFence$$PassThrough codechicken/multipart/TMultiPart] []
    RETURN
    MAXSTACK = 2
    MAXLOCALS = 2

  // access flags 0x9
  public static partRemoved(LTFence$$PassThrough;Lcodechicken/multipart/TMultiPart;I)V
    ALOAD 0
    ALOAD 1
    ILOAD 2
    INVOKEINTERFACE TFence$$PassThrough.TFence$$PassThrough$$super$partRemoved (Lcodechicken/multipart/TMultiPart;I)V
    ALOAD 1
    ALOAD 0
    INVOKEINTERFACE TFence$$PassThrough.TFence$$PassThrough$$impl ()Lcom/rwtema/extrautils/multipart/microblock/IFence;
    IF_ACMPNE L0
    ALOAD 0
    ACONST_NULL
    INVOKEINTERFACE TFence$$PassThrough.TFence$$PassThrough$$impl_$eq (Lcom/rwtema/extrautils/multipart/microblock/IFence;)V
   L0
   FRAME FULL [TFence$$PassThrough codechicken/multipart/TMultiPart I] []
    RETURN
    MAXSTACK = 3
    MAXLOCALS = 3

  // access flags 0x9
  public static canAddPart(LTFence$$PassThrough;Lcodechicken/multipart/TMultiPart;)Z
    ALOAD 0
    INVOKEINTERFACE TFence$$PassThrough.TFence$$PassThrough$$impl ()Lcom/rwtema/extrautils/multipart/microblock/IFence;
    IFNULL L0
    ALOAD 1
    INSTANCEOF com/rwtema/extrautils/multipart/microblock/IFence
    IFEQ L0
    ICONST_0
    IRETURN
   L0
   FRAME FULL [TFence$$PassThrough codechicken/multipart/TMultiPart] []
    ALOAD 0
    ALOAD 1
    INVOKEINTERFACE TFence$$PassThrough.TFence$$PassThrough$$super$canAddPart (Lcodechicken/multipart/TMultiPart;)Z
    IRETURN
    MAXSTACK = 2
    MAXLOCALS = 2

  // access flags 0x9
  public static copyFrom(LTFence$$PassThrough;Lcodechicken/multipart/TileMultipart;)V
    ALOAD 0
    ALOAD 1
    INVOKEINTERFACE TFence$$PassThrough.TFence$$PassThrough$$super$copyFrom (Lcodechicken/multipart/TileMultipart;)V
    ALOAD 1
    INSTANCEOF TFence$$PassThrough
    IFEQ L0
    ALOAD 0
    ALOAD 1
    INVOKEINTERFACE TFence$$PassThrough.TFence$$PassThrough$$impl ()Lcom/rwtema/extrautils/multipart/microblock/IFence;
    INVOKEINTERFACE TFence$$PassThrough.TFence$$PassThrough$$impl_$eq (Lcom/rwtema/extrautils/multipart/microblock/IFence;)V
   L0
    RETURN
    MAXSTACK = 2
    MAXLOCALS = 2
}
