// class version 50.0 (50)
// access flags 0x401
public abstract class TFilterPipe$$PassThrough$class {


  // access flags 0x9
  public static $init$(LTFilterPipe$$PassThrough;)V
    RETURN
    MAXSTACK = 1
    MAXLOCALS = 1

  // access flags 0x9
  public static bindPart(LTFilterPipe$$PassThrough;Lcodechicken/multipart/TMultiPart;)V
    ALOAD 0
    ALOAD 1
    INVOKEINTERFACE TFilterPipe$$PassThrough.TFilterPipe$$PassThrough$$super$bindPart (Lcodechicken/multipart/TMultiPart;)V
    ALOAD 1
    INSTANCEOF com/rwtema/extrautils/tileentity/transfernodes/pipes/IFilterPipe
    IFEQ L0
    ALOAD 0
    ALOAD 1
    CHECKCAST com/rwtema/extrautils/tileentity/transfernodes/pipes/IFilterPipe
    INVOKEINTERFACE TFilterPipe$$PassThrough.TFilterPipe$$PassThrough$$impl_$eq (Lcom/rwtema/extrautils/tileentity/transfernodes/pipes/IFilterPipe;)V
   L0
   FRAME FULL [TFilterPipe$$PassThrough codechicken/multipart/TMultiPart] []
    RETURN
    MAXSTACK = 2
    MAXLOCALS = 2

  // access flags 0x9
  public static partRemoved(LTFilterPipe$$PassThrough;Lcodechicken/multipart/TMultiPart;I)V
    ALOAD 0
    ALOAD 1
    ILOAD 2
    INVOKEINTERFACE TFilterPipe$$PassThrough.TFilterPipe$$PassThrough$$super$partRemoved (Lcodechicken/multipart/TMultiPart;I)V
    ALOAD 1
    ALOAD 0
    INVOKEINTERFACE TFilterPipe$$PassThrough.TFilterPipe$$PassThrough$$impl ()Lcom/rwtema/extrautils/tileentity/transfernodes/pipes/IFilterPipe;
    IF_ACMPNE L0
    ALOAD 0
    ACONST_NULL
    INVOKEINTERFACE TFilterPipe$$PassThrough.TFilterPipe$$PassThrough$$impl_$eq (Lcom/rwtema/extrautils/tileentity/transfernodes/pipes/IFilterPipe;)V
   L0
   FRAME FULL [TFilterPipe$$PassThrough codechicken/multipart/TMultiPart I] []
    RETURN
    MAXSTACK = 3
    MAXLOCALS = 3

  // access flags 0x9
  public static canAddPart(LTFilterPipe$$PassThrough;Lcodechicken/multipart/TMultiPart;)Z
    ALOAD 0
    INVOKEINTERFACE TFilterPipe$$PassThrough.TFilterPipe$$PassThrough$$impl ()Lcom/rwtema/extrautils/tileentity/transfernodes/pipes/IFilterPipe;
    IFNULL L0
    ALOAD 1
    INSTANCEOF com/rwtema/extrautils/tileentity/transfernodes/pipes/IFilterPipe
    IFEQ L0
    ICONST_0
    IRETURN
   L0
   FRAME FULL [TFilterPipe$$PassThrough codechicken/multipart/TMultiPart] []
    ALOAD 0
    ALOAD 1
    INVOKEINTERFACE TFilterPipe$$PassThrough.TFilterPipe$$PassThrough$$super$canAddPart (Lcodechicken/multipart/TMultiPart;)Z
    IRETURN
    MAXSTACK = 2
    MAXLOCALS = 2

  // access flags 0x9
  public static getFilterInventory(LTFilterPipe$$PassThrough;Lnet/minecraft/world/IBlockAccess;III)Lnet/minecraft/inventory/IInventory;
    ALOAD 0
    INVOKEINTERFACE TFilterPipe$$PassThrough.TFilterPipe$$PassThrough$$impl ()Lcom/rwtema/extrautils/tileentity/transfernodes/pipes/IFilterPipe;
    ALOAD 1
    ILOAD 2
    ILOAD 3
    ILOAD 4
    INVOKEINTERFACE com/rwtema/extrautils/tileentity/transfernodes/pipes/IFilterPipe.getFilterInventory (Lnet/minecraft/world/IBlockAccess;III)Lnet/minecraft/inventory/IInventory;
    ARETURN
    MAXSTACK = 5
    MAXLOCALS = 5

  // access flags 0x9
  public static copyFrom(LTFilterPipe$$PassThrough;Lcodechicken/multipart/TileMultipart;)V
    ALOAD 0
    ALOAD 1
    INVOKEINTERFACE TFilterPipe$$PassThrough.TFilterPipe$$PassThrough$$super$copyFrom (Lcodechicken/multipart/TileMultipart;)V
    ALOAD 1
    INSTANCEOF TFilterPipe$$PassThrough
    IFEQ L0
    ALOAD 0
    ALOAD 1
    INVOKEINTERFACE TFilterPipe$$PassThrough.TFilterPipe$$PassThrough$$impl ()Lcom/rwtema/extrautils/tileentity/transfernodes/pipes/IFilterPipe;
    INVOKEINTERFACE TFilterPipe$$PassThrough.TFilterPipe$$PassThrough$$impl_$eq (Lcom/rwtema/extrautils/tileentity/transfernodes/pipes/IFilterPipe;)V
   L0
    RETURN
    MAXSTACK = 2
    MAXLOCALS = 2
}
