// class version 50.0 (50)
// access flags 0x401
public abstract class TNodeEnergy$$PassThrough$class {


  // access flags 0x9
  public static $init$(LTNodeEnergy$$PassThrough;)V
    RETURN
    MAXSTACK = 1
    MAXLOCALS = 1

  // access flags 0x9
  public static bindPart(LTNodeEnergy$$PassThrough;Lcodechicken/multipart/TMultiPart;)V
    ALOAD 0
    ALOAD 1
    INVOKEINTERFACE TNodeEnergy$$PassThrough.TNodeEnergy$$PassThrough$$super$bindPart (Lcodechicken/multipart/TMultiPart;)V
    ALOAD 1
    INSTANCEOF com/rwtema/extrautils/tileentity/transfernodes/nodebuffer/INodeEnergy
    IFEQ L0
    ALOAD 0
    ALOAD 1
    CHECKCAST com/rwtema/extrautils/tileentity/transfernodes/nodebuffer/INodeEnergy
    INVOKEINTERFACE TNodeEnergy$$PassThrough.TNodeEnergy$$PassThrough$$impl_$eq (Lcom/rwtema/extrautils/tileentity/transfernodes/nodebuffer/INodeEnergy;)V
   L0
   FRAME FULL [TNodeEnergy$$PassThrough codechicken/multipart/TMultiPart] []
    RETURN
    MAXSTACK = 2
    MAXLOCALS = 2

  // access flags 0x9
  public static partRemoved(LTNodeEnergy$$PassThrough;Lcodechicken/multipart/TMultiPart;I)V
    ALOAD 0
    ALOAD 1
    ILOAD 2
    INVOKEINTERFACE TNodeEnergy$$PassThrough.TNodeEnergy$$PassThrough$$super$partRemoved (Lcodechicken/multipart/TMultiPart;I)V
    ALOAD 1
    ALOAD 0
    INVOKEINTERFACE TNodeEnergy$$PassThrough.TNodeEnergy$$PassThrough$$impl ()Lcom/rwtema/extrautils/tileentity/transfernodes/nodebuffer/INodeEnergy;
    IF_ACMPNE L0
    ALOAD 0
    ACONST_NULL
    INVOKEINTERFACE TNodeEnergy$$PassThrough.TNodeEnergy$$PassThrough$$impl_$eq (Lcom/rwtema/extrautils/tileentity/transfernodes/nodebuffer/INodeEnergy;)V
   L0
   FRAME FULL [TNodeEnergy$$PassThrough codechicken/multipart/TMultiPart I] []
    RETURN
    MAXSTACK = 3
    MAXLOCALS = 3

  // access flags 0x9
  public static canAddPart(LTNodeEnergy$$PassThrough;Lcodechicken/multipart/TMultiPart;)Z
    ALOAD 0
    INVOKEINTERFACE TNodeEnergy$$PassThrough.TNodeEnergy$$PassThrough$$impl ()Lcom/rwtema/extrautils/tileentity/transfernodes/nodebuffer/INodeEnergy;
    IFNULL L0
    ALOAD 1
    INSTANCEOF com/rwtema/extrautils/tileentity/transfernodes/nodebuffer/INodeEnergy
    IFEQ L0
    ICONST_0
    IRETURN
   L0
   FRAME FULL [TNodeEnergy$$PassThrough codechicken/multipart/TMultiPart] []
    ALOAD 0
    ALOAD 1
    INVOKEINTERFACE TNodeEnergy$$PassThrough.TNodeEnergy$$PassThrough$$super$canAddPart (Lcodechicken/multipart/TMultiPart;)Z
    IRETURN
    MAXSTACK = 2
    MAXLOCALS = 2

  // access flags 0x9
  public static getNode(LTNodeEnergy$$PassThrough;)Lcom/rwtema/extrautils/tileentity/transfernodes/TileEntityTransferNodeEnergy;
    ALOAD 0
    INVOKEINTERFACE TNodeEnergy$$PassThrough.TNodeEnergy$$PassThrough$$impl ()Lcom/rwtema/extrautils/tileentity/transfernodes/nodebuffer/INodeEnergy;
    INVOKEINTERFACE com/rwtema/extrautils/tileentity/transfernodes/nodebuffer/INodeEnergy.getNode ()Lcom/rwtema/extrautils/tileentity/transfernodes/TileEntityTransferNodeEnergy;
    ARETURN
    MAXSTACK = 1
    MAXLOCALS = 1

  // access flags 0x9
  public static copyFrom(LTNodeEnergy$$PassThrough;Lcodechicken/multipart/TileMultipart;)V
    ALOAD 0
    ALOAD 1
    INVOKEINTERFACE TNodeEnergy$$PassThrough.TNodeEnergy$$PassThrough$$super$copyFrom (Lcodechicken/multipart/TileMultipart;)V
    ALOAD 1
    INSTANCEOF TNodeEnergy$$PassThrough
    IFEQ L0
    ALOAD 0
    ALOAD 1
    INVOKEINTERFACE TNodeEnergy$$PassThrough.TNodeEnergy$$PassThrough$$impl ()Lcom/rwtema/extrautils/tileentity/transfernodes/nodebuffer/INodeEnergy;
    INVOKEINTERFACE TNodeEnergy$$PassThrough.TNodeEnergy$$PassThrough$$impl_$eq (Lcom/rwtema/extrautils/tileentity/transfernodes/nodebuffer/INodeEnergy;)V
   L0
    RETURN
    MAXSTACK = 2
    MAXLOCALS = 2
}
