// class version 50.0 (50)
// access flags 0x401
public abstract class TNodeInventory$$PassThrough$class {


  // access flags 0x9
  public static $init$(LTNodeInventory$$PassThrough;)V
    RETURN
    MAXSTACK = 1
    MAXLOCALS = 1

  // access flags 0x9
  public static bindPart(LTNodeInventory$$PassThrough;Lcodechicken/multipart/TMultiPart;)V
    ALOAD 0
    ALOAD 1
    INVOKEINTERFACE TNodeInventory$$PassThrough.TNodeInventory$$PassThrough$$super$bindPart (Lcodechicken/multipart/TMultiPart;)V
    ALOAD 1
    INSTANCEOF com/rwtema/extrautils/tileentity/transfernodes/nodebuffer/INodeInventory
    IFEQ L0
    ALOAD 0
    ALOAD 1
    CHECKCAST com/rwtema/extrautils/tileentity/transfernodes/nodebuffer/INodeInventory
    INVOKEINTERFACE TNodeInventory$$PassThrough.TNodeInventory$$PassThrough$$impl_$eq (Lcom/rwtema/extrautils/tileentity/transfernodes/nodebuffer/INodeInventory;)V
   L0
   FRAME FULL [TNodeInventory$$PassThrough codechicken/multipart/TMultiPart] []
    RETURN
    MAXSTACK = 2
    MAXLOCALS = 2

  // access flags 0x9
  public static partRemoved(LTNodeInventory$$PassThrough;Lcodechicken/multipart/TMultiPart;I)V
    ALOAD 0
    ALOAD 1
    ILOAD 2
    INVOKEINTERFACE TNodeInventory$$PassThrough.TNodeInventory$$PassThrough$$super$partRemoved (Lcodechicken/multipart/TMultiPart;I)V
    ALOAD 1
    ALOAD 0
    INVOKEINTERFACE TNodeInventory$$PassThrough.TNodeInventory$$PassThrough$$impl ()Lcom/rwtema/extrautils/tileentity/transfernodes/nodebuffer/INodeInventory;
    IF_ACMPNE L0
    ALOAD 0
    ACONST_NULL
    INVOKEINTERFACE TNodeInventory$$PassThrough.TNodeInventory$$PassThrough$$impl_$eq (Lcom/rwtema/extrautils/tileentity/transfernodes/nodebuffer/INodeInventory;)V
   L0
   FRAME FULL [TNodeInventory$$PassThrough codechicken/multipart/TMultiPart I] []
    RETURN
    MAXSTACK = 3
    MAXLOCALS = 3

  // access flags 0x9
  public static canAddPart(LTNodeInventory$$PassThrough;Lcodechicken/multipart/TMultiPart;)Z
    ALOAD 0
    INVOKEINTERFACE TNodeInventory$$PassThrough.TNodeInventory$$PassThrough$$impl ()Lcom/rwtema/extrautils/tileentity/transfernodes/nodebuffer/INodeInventory;
    IFNULL L0
    ALOAD 1
    INSTANCEOF com/rwtema/extrautils/tileentity/transfernodes/nodebuffer/INodeInventory
    IFEQ L0
    ICONST_0
    IRETURN
   L0
   FRAME FULL [TNodeInventory$$PassThrough codechicken/multipart/TMultiPart] []
    ALOAD 0
    ALOAD 1
    INVOKEINTERFACE TNodeInventory$$PassThrough.TNodeInventory$$PassThrough$$super$canAddPart (Lcodechicken/multipart/TMultiPart;)Z
    IRETURN
    MAXSTACK = 2
    MAXLOCALS = 2

  // access flags 0x9
  public static getNode(LTNodeInventory$$PassThrough;)Lcom/rwtema/extrautils/tileentity/transfernodes/TileEntityTransferNodeInventory;
    ALOAD 0
    INVOKEINTERFACE TNodeInventory$$PassThrough.TNodeInventory$$PassThrough$$impl ()Lcom/rwtema/extrautils/tileentity/transfernodes/nodebuffer/INodeInventory;
    INVOKEINTERFACE com/rwtema/extrautils/tileentity/transfernodes/nodebuffer/INodeInventory.getNode ()Lcom/rwtema/extrautils/tileentity/transfernodes/TileEntityTransferNodeInventory;
    ARETURN
    MAXSTACK = 1
    MAXLOCALS = 1

  // access flags 0x9
  public static copyFrom(LTNodeInventory$$PassThrough;Lcodechicken/multipart/TileMultipart;)V
    ALOAD 0
    ALOAD 1
    INVOKEINTERFACE TNodeInventory$$PassThrough.TNodeInventory$$PassThrough$$super$copyFrom (Lcodechicken/multipart/TileMultipart;)V
    ALOAD 1
    INSTANCEOF TNodeInventory$$PassThrough
    IFEQ L0
    ALOAD 0
    ALOAD 1
    INVOKEINTERFACE TNodeInventory$$PassThrough.TNodeInventory$$PassThrough$$impl ()Lcom/rwtema/extrautils/tileentity/transfernodes/nodebuffer/INodeInventory;
    INVOKEINTERFACE TNodeInventory$$PassThrough.TNodeInventory$$PassThrough$$impl_$eq (Lcom/rwtema/extrautils/tileentity/transfernodes/nodebuffer/INodeInventory;)V
   L0
    RETURN
    MAXSTACK = 2
    MAXLOCALS = 2
}
