// class version 50.0 (50)
// access flags 0x401
public abstract class TPipe$$PassThrough$class {


  // access flags 0x9
  public static $init$(LTPipe$$PassThrough;)V
    RETURN
    MAXSTACK = 1
    MAXLOCALS = 1

  // access flags 0x9
  public static bindPart(LTPipe$$PassThrough;Lcodechicken/multipart/TMultiPart;)V
    ALOAD 0
    ALOAD 1
    INVOKEINTERFACE TPipe$$PassThrough.TPipe$$PassThrough$$super$bindPart (Lcodechicken/multipart/TMultiPart;)V
    ALOAD 1
    INSTANCEOF com/rwtema/extrautils/tileentity/transfernodes/pipes/IPipe
    IFEQ L0
    ALOAD 0
    ALOAD 1
    CHECKCAST com/rwtema/extrautils/tileentity/transfernodes/pipes/IPipe
    INVOKEINTERFACE TPipe$$PassThrough.TPipe$$PassThrough$$impl_$eq (Lcom/rwtema/extrautils/tileentity/transfernodes/pipes/IPipe;)V
   L0
   FRAME FULL [TPipe$$PassThrough codechicken/multipart/TMultiPart] []
    RETURN
    MAXSTACK = 2
    MAXLOCALS = 2

  // access flags 0x9
  public static partRemoved(LTPipe$$PassThrough;Lcodechicken/multipart/TMultiPart;I)V
    ALOAD 0
    ALOAD 1
    ILOAD 2
    INVOKEINTERFACE TPipe$$PassThrough.TPipe$$PassThrough$$super$partRemoved (Lcodechicken/multipart/TMultiPart;I)V
    ALOAD 1
    ALOAD 0
    INVOKEINTERFACE TPipe$$PassThrough.TPipe$$PassThrough$$impl ()Lcom/rwtema/extrautils/tileentity/transfernodes/pipes/IPipe;
    IF_ACMPNE L0
    ALOAD 0
    ACONST_NULL
    INVOKEINTERFACE TPipe$$PassThrough.TPipe$$PassThrough$$impl_$eq (Lcom/rwtema/extrautils/tileentity/transfernodes/pipes/IPipe;)V
   L0
   FRAME FULL [TPipe$$PassThrough codechicken/multipart/TMultiPart I] []
    RETURN
    MAXSTACK = 3
    MAXLOCALS = 3

  // access flags 0x9
  public static canAddPart(LTPipe$$PassThrough;Lcodechicken/multipart/TMultiPart;)Z
    ALOAD 0
    INVOKEINTERFACE TPipe$$PassThrough.TPipe$$PassThrough$$impl ()Lcom/rwtema/extrautils/tileentity/transfernodes/pipes/IPipe;
    IFNULL L0
    ALOAD 1
    INSTANCEOF com/rwtema/extrautils/tileentity/transfernodes/pipes/IPipe
    IFEQ L0
    ICONST_0
    IRETURN
   L0
   FRAME FULL [TPipe$$PassThrough codechicken/multipart/TMultiPart] []
    ALOAD 0
    ALOAD 1
    INVOKEINTERFACE TPipe$$PassThrough.TPipe$$PassThrough$$super$canAddPart (Lcodechicken/multipart/TMultiPart;)Z
    IRETURN
    MAXSTACK = 2
    MAXLOCALS = 2

  // access flags 0x9
  public static getFilterInventory(LTPipe$$PassThrough;Lnet/minecraft/world/IBlockAccess;III)Lnet/minecraft/inventory/IInventory;
    ALOAD 0
    INVOKEINTERFACE TPipe$$PassThrough.TPipe$$PassThrough$$impl ()Lcom/rwtema/extrautils/tileentity/transfernodes/pipes/IPipe;
    ALOAD 1
    ILOAD 2
    ILOAD 3
    ILOAD 4
    INVOKEINTERFACE com/rwtema/extrautils/tileentity/transfernodes/pipes/IPipe.getFilterInventory (Lnet/minecraft/world/IBlockAccess;III)Lnet/minecraft/inventory/IInventory;
    ARETURN
    MAXSTACK = 5
    MAXLOCALS = 5

  // access flags 0x9
  public static getPipeType(LTPipe$$PassThrough;)Ljava/lang/String;
    ALOAD 0
    INVOKEINTERFACE TPipe$$PassThrough.TPipe$$PassThrough$$impl ()Lcom/rwtema/extrautils/tileentity/transfernodes/pipes/IPipe;
    INVOKEINTERFACE com/rwtema/extrautils/tileentity/transfernodes/pipes/IPipe.getPipeType ()Ljava/lang/String;
    ARETURN
    MAXSTACK = 1
    MAXLOCALS = 1

  // access flags 0x9
  public static limitTransfer(LTPipe$$PassThrough;Lnet/minecraft/tileentity/TileEntity;Lnet/minecraftforge/common/util/ForgeDirection;Lcom/rwtema/extrautils/tileentity/transfernodes/nodebuffer/INodeBuffer;)I
    ALOAD 0
    INVOKEINTERFACE TPipe$$PassThrough.TPipe$$PassThrough$$impl ()Lcom/rwtema/extrautils/tileentity/transfernodes/pipes/IPipe;
    ALOAD 1
    ALOAD 2
    ALOAD 3
    INVOKEINTERFACE com/rwtema/extrautils/tileentity/transfernodes/pipes/IPipe.limitTransfer (Lnet/minecraft/tileentity/TileEntity;Lnet/minecraftforge/common/util/ForgeDirection;Lcom/rwtema/extrautils/tileentity/transfernodes/nodebuffer/INodeBuffer;)I
    IRETURN
    MAXSTACK = 4
    MAXLOCALS = 4

  // access flags 0x9
  public static canInput(LTPipe$$PassThrough;Lnet/minecraft/world/IBlockAccess;IIILnet/minecraftforge/common/util/ForgeDirection;)Z
    ALOAD 0
    INVOKEINTERFACE TPipe$$PassThrough.TPipe$$PassThrough$$impl ()Lcom/rwtema/extrautils/tileentity/transfernodes/pipes/IPipe;
    ALOAD 1
    ILOAD 2
    ILOAD 3
    ILOAD 4
    ALOAD 5
    INVOKEINTERFACE com/rwtema/extrautils/tileentity/transfernodes/pipes/IPipe.canInput (Lnet/minecraft/world/IBlockAccess;IIILnet/minecraftforge/common/util/ForgeDirection;)Z
    IRETURN
    MAXSTACK = 6
    MAXLOCALS = 6

  // access flags 0x9
  public static shouldConnectToTile(LTPipe$$PassThrough;Lnet/minecraft/world/IBlockAccess;IIILnet/minecraftforge/common/util/ForgeDirection;)Z
    ALOAD 0
    INVOKEINTERFACE TPipe$$PassThrough.TPipe$$PassThrough$$impl ()Lcom/rwtema/extrautils/tileentity/transfernodes/pipes/IPipe;
    ALOAD 1
    ILOAD 2
    ILOAD 3
    ILOAD 4
    ALOAD 5
    INVOKEINTERFACE com/rwtema/extrautils/tileentity/transfernodes/pipes/IPipe.shouldConnectToTile (Lnet/minecraft/world/IBlockAccess;IIILnet/minecraftforge/common/util/ForgeDirection;)Z
    IRETURN
    MAXSTACK = 6
    MAXLOCALS = 6

  // access flags 0x9
  public static canOutput(LTPipe$$PassThrough;Lnet/minecraft/world/IBlockAccess;IIILnet/minecraftforge/common/util/ForgeDirection;)Z
    ALOAD 0
    INVOKEINTERFACE TPipe$$PassThrough.TPipe$$PassThrough$$impl ()Lcom/rwtema/extrautils/tileentity/transfernodes/pipes/IPipe;
    ALOAD 1
    ILOAD 2
    ILOAD 3
    ILOAD 4
    ALOAD 5
    INVOKEINTERFACE com/rwtema/extrautils/tileentity/transfernodes/pipes/IPipe.canOutput (Lnet/minecraft/world/IBlockAccess;IIILnet/minecraftforge/common/util/ForgeDirection;)Z
    IRETURN
    MAXSTACK = 6
    MAXLOCALS = 6

  // access flags 0x9
  public static getOutputDirections(LTPipe$$PassThrough;Lnet/minecraft/world/IBlockAccess;IIILnet/minecraftforge/common/util/ForgeDirection;Lcom/rwtema/extrautils/tileentity/transfernodes/nodebuffer/INodeBuffer;)Ljava/util/ArrayList;
    ALOAD 0
    INVOKEINTERFACE TPipe$$PassThrough.TPipe$$PassThrough$$impl ()Lcom/rwtema/extrautils/tileentity/transfernodes/pipes/IPipe;
    ALOAD 1
    ILOAD 2
    ILOAD 3
    ILOAD 4
    ALOAD 5
    ALOAD 6
    INVOKEINTERFACE com/rwtema/extrautils/tileentity/transfernodes/pipes/IPipe.getOutputDirections (Lnet/minecraft/world/IBlockAccess;IIILnet/minecraftforge/common/util/ForgeDirection;Lcom/rwtema/extrautils/tileentity/transfernodes/nodebuffer/INodeBuffer;)Ljava/util/ArrayList;
    ARETURN
    MAXSTACK = 7
    MAXLOCALS = 7

  // access flags 0x9
  public static transferItems(LTPipe$$PassThrough;Lnet/minecraft/world/IBlockAccess;IIILnet/minecraftforge/common/util/ForgeDirection;Lcom/rwtema/extrautils/tileentity/transfernodes/nodebuffer/INodeBuffer;)Z
    ALOAD 0
    INVOKEINTERFACE TPipe$$PassThrough.TPipe$$PassThrough$$impl ()Lcom/rwtema/extrautils/tileentity/transfernodes/pipes/IPipe;
    ALOAD 1
    ILOAD 2
    ILOAD 3
    ILOAD 4
    ALOAD 5
    ALOAD 6
    INVOKEINTERFACE com/rwtema/extrautils/tileentity/transfernodes/pipes/IPipe.transferItems (Lnet/minecraft/world/IBlockAccess;IIILnet/minecraftforge/common/util/ForgeDirection;Lcom/rwtema/extrautils/tileentity/transfernodes/nodebuffer/INodeBuffer;)Z
    IRETURN
    MAXSTACK = 7
    MAXLOCALS = 7

  // access flags 0x9
  public static copyFrom(LTPipe$$PassThrough;Lcodechicken/multipart/TileMultipart;)V
    ALOAD 0
    ALOAD 1
    INVOKEINTERFACE TPipe$$PassThrough.TPipe$$PassThrough$$super$copyFrom (Lcodechicken/multipart/TileMultipart;)V
    ALOAD 1
    INSTANCEOF TPipe$$PassThrough
    IFEQ L0
    ALOAD 0
    ALOAD 1
    INVOKEINTERFACE TPipe$$PassThrough.TPipe$$PassThrough$$impl ()Lcom/rwtema/extrautils/tileentity/transfernodes/pipes/IPipe;
    INVOKEINTERFACE TPipe$$PassThrough.TPipe$$PassThrough$$impl_$eq (Lcom/rwtema/extrautils/tileentity/transfernodes/pipes/IPipe;)V
   L0
    RETURN
    MAXSTACK = 2
    MAXLOCALS = 2
}
