// class version 50.0 (50)
// access flags 0x401
public abstract class TSidedEnvironment$$PassThrough$class {


  // access flags 0x9
  public static $init$(LTSidedEnvironment$$PassThrough;)V
    RETURN
    MAXSTACK = 1
    MAXLOCALS = 1

  // access flags 0x9
  public static bindPart(LTSidedEnvironment$$PassThrough;Lcodechicken/multipart/TMultiPart;)V
    ALOAD 0
    ALOAD 1
    INVOKEINTERFACE TSidedEnvironment$$PassThrough.TSidedEnvironment$$PassThrough$$super$bindPart (Lcodechicken/multipart/TMultiPart;)V
    ALOAD 1
    INSTANCEOF li/cil/oc/api/network/SidedEnvironment
    IFEQ L0
    ALOAD 0
    ALOAD 1
    CHECKCAST li/cil/oc/api/network/SidedEnvironment
    INVOKEINTERFACE TSidedEnvironment$$PassThrough.TSidedEnvironment$$PassThrough$$impl_$eq (Lli/cil/oc/api/network/SidedEnvironment;)V
   L0
   FRAME FULL [TSidedEnvironment$$PassThrough codechicken/multipart/TMultiPart] []
    RETURN
    MAXSTACK = 2
    MAXLOCALS = 2

  // access flags 0x9
  public static partRemoved(LTSidedEnvironment$$PassThrough;Lcodechicken/multipart/TMultiPart;I)V
    ALOAD 0
    ALOAD 1
    ILOAD 2
    INVOKEINTERFACE TSidedEnvironment$$PassThrough.TSidedEnvironment$$PassThrough$$super$partRemoved (Lcodechicken/multipart/TMultiPart;I)V
    ALOAD 1
    ALOAD 0
    INVOKEINTERFACE TSidedEnvironment$$PassThrough.TSidedEnvironment$$PassThrough$$impl ()Lli/cil/oc/api/network/SidedEnvironment;
    IF_ACMPNE L0
    ALOAD 0
    ACONST_NULL
    INVOKEINTERFACE TSidedEnvironment$$PassThrough.TSidedEnvironment$$PassThrough$$impl_$eq (Lli/cil/oc/api/network/SidedEnvironment;)V
   L0
   FRAME FULL [TSidedEnvironment$$PassThrough codechicken/multipart/TMultiPart I] []
    RETURN
    MAXSTACK = 3
    MAXLOCALS = 3

  // access flags 0x9
  public static canAddPart(LTSidedEnvironment$$PassThrough;Lcodechicken/multipart/TMultiPart;)Z
    ALOAD 0
    INVOKEINTERFACE TSidedEnvironment$$PassThrough.TSidedEnvironment$$PassThrough$$impl ()Lli/cil/oc/api/network/SidedEnvironment;
    IFNULL L0
    ALOAD 1
    INSTANCEOF li/cil/oc/api/network/SidedEnvironment
    IFEQ L0
    ICONST_0
    IRETURN
   L0
   FRAME FULL [TSidedEnvironment$$PassThrough codechicken/multipart/TMultiPart] []
    ALOAD 0
    ALOAD 1
    INVOKEINTERFACE TSidedEnvironment$$PassThrough.TSidedEnvironment$$PassThrough$$super$canAddPart (Lcodechicken/multipart/TMultiPart;)Z
    IRETURN
    MAXSTACK = 2
    MAXLOCALS = 2

  // access flags 0x9
  public static sidedNode(LTSidedEnvironment$$PassThrough;Lnet/minecraftforge/common/util/ForgeDirection;)Lli/cil/oc/api/network/Node;
    ALOAD 0
    INVOKEINTERFACE TSidedEnvironment$$PassThrough.TSidedEnvironment$$PassThrough$$impl ()Lli/cil/oc/api/network/SidedEnvironment;
    ALOAD 1
    INVOKEINTERFACE li/cil/oc/api/network/SidedEnvironment.sidedNode (Lnet/minecraftforge/common/util/ForgeDirection;)Lli/cil/oc/api/network/Node;
    ARETURN
    MAXSTACK = 2
    MAXLOCALS = 2

  // access flags 0x9
  public static canConnect(LTSidedEnvironment$$PassThrough;Lnet/minecraftforge/common/util/ForgeDirection;)Z
    ALOAD 0
    INVOKEINTERFACE TSidedEnvironment$$PassThrough.TSidedEnvironment$$PassThrough$$impl ()Lli/cil/oc/api/network/SidedEnvironment;
    ALOAD 1
    INVOKEINTERFACE li/cil/oc/api/network/SidedEnvironment.canConnect (Lnet/minecraftforge/common/util/ForgeDirection;)Z
    IRETURN
    MAXSTACK = 2
    MAXLOCALS = 2

  // access flags 0x9
  public static copyFrom(LTSidedEnvironment$$PassThrough;Lcodechicken/multipart/TileMultipart;)V
    ALOAD 0
    ALOAD 1
    INVOKEINTERFACE TSidedEnvironment$$PassThrough.TSidedEnvironment$$PassThrough$$super$copyFrom (Lcodechicken/multipart/TileMultipart;)V
    ALOAD 1
    INSTANCEOF TSidedEnvironment$$PassThrough
    IFEQ L0
    ALOAD 0
    ALOAD 1
    INVOKEINTERFACE TSidedEnvironment$$PassThrough.TSidedEnvironment$$PassThrough$$impl ()Lli/cil/oc/api/network/SidedEnvironment;
    INVOKEINTERFACE TSidedEnvironment$$PassThrough.TSidedEnvironment$$PassThrough$$impl_$eq (Lli/cil/oc/api/network/SidedEnvironment;)V
   L0
    RETURN
    MAXSTACK = 2
    MAXLOCALS = 2
}
