// class version 50.0 (50)
// access flags 0x401
public abstract class TWall$$PassThrough$class {


  // access flags 0x9
  public static $init$(LTWall$$PassThrough;)V
    RETURN
    MAXSTACK = 1
    MAXLOCALS = 1

  // access flags 0x9
  public static bindPart(LTWall$$PassThrough;Lcodechicken/multipart/TMultiPart;)V
    ALOAD 0
    ALOAD 1
    INVOKEINTERFACE TWall$$PassThrough.TWall$$PassThrough$$super$bindPart (Lcodechicken/multipart/TMultiPart;)V
    ALOAD 1
    INSTANCEOF com/rwtema/extrautils/multipart/microblock/IWall
    IFEQ L0
    ALOAD 0
    ALOAD 1
    CHECKCAST com/rwtema/extrautils/multipart/microblock/IWall
    INVOKEINTERFACE TWall$$PassThrough.TWall$$PassThrough$$impl_$eq (Lcom/rwtema/extrautils/multipart/microblock/IWall;)V
   L0
   FRAME FULL [TWall$$PassThrough codechicken/multipart/TMultiPart] []
    RETURN
    MAXSTACK = 2
    MAXLOCALS = 2

  // access flags 0x9
  public static partRemoved(LTWall$$PassThrough;Lcodechicken/multipart/TMultiPart;I)V
    ALOAD 0
    ALOAD 1
    ILOAD 2
    INVOKEINTERFACE TWall$$PassThrough.TWall$$PassThrough$$super$partRemoved (Lcodechicken/multipart/TMultiPart;I)V
    ALOAD 1
    ALOAD 0
    INVOKEINTERFACE TWall$$PassThrough.TWall$$PassThrough$$impl ()Lcom/rwtema/extrautils/multipart/microblock/IWall;
    IF_ACMPNE L0
    ALOAD 0
    ACONST_NULL
    INVOKEINTERFACE TWall$$PassThrough.TWall$$PassThrough$$impl_$eq (Lcom/rwtema/extrautils/multipart/microblock/IWall;)V
   L0
   FRAME FULL [TWall$$PassThrough codechicken/multipart/TMultiPart I] []
    RETURN
    MAXSTACK = 3
    MAXLOCALS = 3

  // access flags 0x9
  public static canAddPart(LTWall$$PassThrough;Lcodechicken/multipart/TMultiPart;)Z
    ALOAD 0
    INVOKEINTERFACE TWall$$PassThrough.TWall$$PassThrough$$impl ()Lcom/rwtema/extrautils/multipart/microblock/IWall;
    IFNULL L0
    ALOAD 1
    INSTANCEOF com/rwtema/extrautils/multipart/microblock/IWall
    IFEQ L0
    ICONST_0
    IRETURN
   L0
   FRAME FULL [TWall$$PassThrough codechicken/multipart/TMultiPart] []
    ALOAD 0
    ALOAD 1
    INVOKEINTERFACE TWall$$PassThrough.TWall$$PassThrough$$super$canAddPart (Lcodechicken/multipart/TMultiPart;)Z
    IRETURN
    MAXSTACK = 2
    MAXLOCALS = 2

  // access flags 0x9
  public static copyFrom(LTWall$$PassThrough;Lcodechicken/multipart/TileMultipart;)V
    ALOAD 0
    ALOAD 1
    INVOKEINTERFACE TWall$$PassThrough.TWall$$PassThrough$$super$copyFrom (Lcodechicken/multipart/TileMultipart;)V
    ALOAD 1
    INSTANCEOF TWall$$PassThrough
    IFEQ L0
    ALOAD 0
    ALOAD 1
    INVOKEINTERFACE TWall$$PassThrough.TWall$$PassThrough$$impl ()Lcom/rwtema/extrautils/multipart/microblock/IWall;
    INVOKEINTERFACE TWall$$PassThrough.TWall$$PassThrough$$impl_$eq (Lcom/rwtema/extrautils/multipart/microblock/IWall;)V
   L0
    RETURN
    MAXSTACK = 2
    MAXLOCALS = 2
}
